quantlplot/__init__.py
quantlplot/pdplot.py
quantlplot-1.8.1.dist-info/LICENSE.txt
quantlplot-1.8.1.dist-info/METADATA
quantlplot-1.8.1.dist-info/WHEEL
quantlplot-1.8.1.dist-info/top_level.txt
quantlplot-1.8.1.dist-info/RECORD
