Metadata-Version: 2.1
Name: quantlplot
Version: 1.8.1
Summary: Finance plotting for Quantl
Home-page: https://github.com/shamazkhan/quantlplot
Author: Shamaz Khan
Author-email: shamaz.khan@outlook.com
License: UNKNOWN
Platform: UNKNOWN
Classifier: Programming Language :: Python :: 3
Classifier: License :: OSI Approved :: MIT License
Classifier: Operating System :: OS Independent
Requires-Dist: pandas
Requires-Dist: PyQt5
Requires-Dist: pyqtgraph (>=0.11.1)
